airtable_cacher/__init__.py
airtable_cacher-1.2.5.dist-info/METADATA
airtable_cacher-1.2.5.dist-info/WHEEL
airtable_cacher-1.2.5.dist-info/top_level.txt
airtable_cacher-1.2.5.dist-info/RECORD
