Metadata-Version: 2.1
Name: airtable-cacher
Version: 1.2.5
Summary: Utility for caching api responses from the airtable-python-wrapper based on airtable-caching by rmountjoy
Home-page: https://github.com/bawpcwpn/AirtableCacher
Author: thuxley
Author-email: thomas.huxley90@gmail.com
License: UNKNOWN
Platform: UNKNOWN
Classifier: Programming Language :: Python :: 3
Classifier: License :: OSI Approved :: MIT License
Classifier: Operating System :: OS Independent
Requires-Python: >=3.6
Requires-Dist: airtable-python-wrapper
